{
  "errors": [
    "./services/htmlBuildBundler/application.js\nModule build failed (from ./node_modules/babel-loader/lib/index.js):\nSyntaxError: static is a reserved word in strict mode (42:12)\n\n\u001b[0m \u001b[90m 40 | \u001b[39m    }\u001b[33m,\u001b[39m \u001b[36mnull\u001b[39m)\u001b[33m,\u001b[39m mountNode\u001b[33m,\u001b[39m \u001b[36mfunction\u001b[39m(){\n \u001b[90m 41 | \u001b[39m      console\u001b[33m.\u001b[39mlog(\u001b[32m'done hydrating'\u001b[39m)\n\u001b[31m\u001b[1m>\u001b[22m\u001b[39m\u001b[90m 42 | \u001b[39m      \u001b[36mconst\u001b[39m static \u001b[33m=\u001b[39m document\u001b[33m.\u001b[39mgetElementById(\u001b[32m'static-container'\u001b[39m)\n \u001b[90m    | \u001b[39m            \u001b[31m\u001b[1m^\u001b[22m\u001b[39m\n \u001b[90m 43 | \u001b[39m      setTimeout(() \u001b[33m=>\u001b[39m {\n \u001b[90m 44 | \u001b[39m        \u001b[36mif\u001b[39m (static) {\n \u001b[90m 45 | \u001b[39m          static\u001b[33m.\u001b[39mremove()\u001b[33m;\u001b[39m\u001b[0m\n\nBabelLoaderError: SyntaxError: static is a reserved word in strict mode (42:12)\n\n\u001b[0m \u001b[90m 40 | \u001b[39m    }\u001b[33m,\u001b[39m \u001b[36mnull\u001b[39m)\u001b[33m,\u001b[39m mountNode\u001b[33m,\u001b[39m \u001b[36mfunction\u001b[39m(){\n \u001b[90m 41 | \u001b[39m      console\u001b[33m.\u001b[39mlog(\u001b[32m'done hydrating'\u001b[39m)\n\u001b[31m\u001b[1m>\u001b[22m\u001b[39m\u001b[90m 42 | \u001b[39m      \u001b[36mconst\u001b[39m static \u001b[33m=\u001b[39m document\u001b[33m.\u001b[39mgetElementById(\u001b[32m'static-container'\u001b[39m)\n \u001b[90m    | \u001b[39m            \u001b[31m\u001b[1m^\u001b[22m\u001b[39m\n \u001b[90m 43 | \u001b[39m      setTimeout(() \u001b[33m=>\u001b[39m {\n \u001b[90m 44 | \u001b[39m        \u001b[36mif\u001b[39m (static) {\n \u001b[90m 45 | \u001b[39m          static\u001b[33m.\u001b[39mremove()\u001b[33m;\u001b[39m\u001b[0m\n\n    at transpile (/Users/rawbin/Documents/Projets/these/peritext/peritext-libs/ovide/node_modules/babel-loader/lib/index.js:65:13)\n    at /Users/rawbin/Documents/Projets/these/peritext/peritext-libs/ovide/node_modules/babel-loader/lib/fs-cache.js:118:18\n    at ReadFileContext.callback (/Users/rawbin/Documents/Projets/these/peritext/peritext-libs/ovide/node_modules/babel-loader/lib/fs-cache.js:31:21)\n    at FSReqCallback.readFileAfterOpen [as oncomplete] (fs.js:239:13)"
  ],
  "warnings": [
  ],
  "version": "4.41.2",
  "hash": "f76b280e2e8a4a26092a",
  "time": 198,
  "builtAt": 1573379026533,
  "publicPath": "",
  "outputPath": "/Users/rawbin/Documents/Projets/these/peritext/peritext-libs/ovide/app/htmlBuilds/single-page-html/callirhoe",
  "assetsByChunkName": {
    "main": "bundle.js"
  },
  "assets": [
    {
      "name": "bundle.js",
      "size": 1632,
      "chunks": [
        0
      ],
      "chunkNames": [
        "main"
      ],
      "info": {
      },
      "emitted": false
    }
  ],
  "filteredAssets": 0,
  "entrypoints": {
    "main": {
      "chunks": [
        0
      ],
      "assets": [
        "bundle.js"
      ],
      "children": {
      },
      "childAssets": {
      }
    }
  },
  "namedChunkGroups": {
    "main": {
      "chunks": [
        0
      ],
      "assets": [
        "bundle.js"
      ],
      "children": {
      },
      "childAssets": {
      }
    }
  },
  "chunks": [
    {
      "id": 0,
      "rendered": true,
      "initial": true,
      "entry": true,
      "size": 973,
      "names": [
        "main"
      ],
      "files": [
        "bundle.js"
      ],
      "hash": "6871ae09e17f1a96add9",
      "siblings": [
      ],
      "parents": [
      ],
      "children": [
      ],
      "childrenByOrder": {
      },
      "modules": [
        {
          "id": 0,
          "identifier": "/Users/rawbin/Documents/Projets/these/peritext/peritext-libs/ovide/node_modules/babel-loader/lib/index.js??ref--4!/Users/rawbin/Documents/Projets/these/peritext/peritext-libs/ovide/services/htmlBuildBundler/application.js",
          "name": "./services/htmlBuildBundler/application.js",
          "index": 0,
          "index2": 0,
          "size": 973,
          "cacheable": true,
          "built": true,
          "optional": false,
          "prefetched": false,
          "chunks": [
            0
          ],
          "issuer": null,
          "issuerId": null,
          "issuerName": null,
          "issuerPath": null,
          "failed": true,
          "errors": 1,
          "warnings": 0,
          "assets": [
          ],
          "reasons": [
            {
              "moduleId": null,
              "moduleIdentifier": null,
              "module": null,
              "moduleName": null,
              "type": "single entry",
              "userRequest": "/Users/rawbin/Documents/Projets/these/peritext/peritext-libs/ovide/services/htmlBuildBundler/application.js",
              "loc": "main"
            }
          ],
          "usedExports": true,
          "providedExports": null,
          "optimizationBailout": [
            "ModuleConcatenation bailout: Module is not an ECMAScript module"
          ],
          "depth": 0,
          "source": "throw new Error(\"Module build failed (from ./node_modules/babel-loader/lib/index.js):\\nSyntaxError: static is a reserved word in strict mode (42:12)\\n\\n\\u001b[0m \\u001b[90m 40 | \\u001b[39m    }\\u001b[33m,\\u001b[39m \\u001b[36mnull\\u001b[39m)\\u001b[33m,\\u001b[39m mountNode\\u001b[33m,\\u001b[39m \\u001b[36mfunction\\u001b[39m(){\\n \\u001b[90m 41 | \\u001b[39m      console\\u001b[33m.\\u001b[39mlog(\\u001b[32m'done hydrating'\\u001b[39m)\\n\\u001b[31m\\u001b[1m>\\u001b[22m\\u001b[39m\\u001b[90m 42 | \\u001b[39m      \\u001b[36mconst\\u001b[39m static \\u001b[33m=\\u001b[39m document\\u001b[33m.\\u001b[39mgetElementById(\\u001b[32m'static-container'\\u001b[39m)\\n \\u001b[90m    | \\u001b[39m            \\u001b[31m\\u001b[1m^\\u001b[22m\\u001b[39m\\n \\u001b[90m 43 | \\u001b[39m      setTimeout(() \\u001b[33m=>\\u001b[39m {\\n \\u001b[90m 44 | \\u001b[39m        \\u001b[36mif\\u001b[39m (static) {\\n \\u001b[90m 45 | \\u001b[39m          static\\u001b[33m.\\u001b[39mremove()\\u001b[33m;\\u001b[39m\\u001b[0m\\n\");"
        }
      ],
      "filteredModules": 0,
      "origins": [
        {
          "module": "",
          "moduleIdentifier": "",
          "moduleName": "",
          "loc": "main",
          "request": "/Users/rawbin/Documents/Projets/these/peritext/peritext-libs/ovide/services/htmlBuildBundler/application.js",
          "reasons": [
          ]
        }
      ]
    }
  ],
  "modules": [
    {
      "id": 0,
      "identifier": "/Users/rawbin/Documents/Projets/these/peritext/peritext-libs/ovide/node_modules/babel-loader/lib/index.js??ref--4!/Users/rawbin/Documents/Projets/these/peritext/peritext-libs/ovide/services/htmlBuildBundler/application.js",
      "name": "./services/htmlBuildBundler/application.js",
      "index": 0,
      "index2": 0,
      "size": 973,
      "cacheable": true,
      "built": true,
      "optional": false,
      "prefetched": false,
      "chunks": [
        0
      ],
      "issuer": null,
      "issuerId": null,
      "issuerName": null,
      "issuerPath": null,
      "failed": true,
      "errors": 1,
      "warnings": 0,
      "assets": [
      ],
      "reasons": [
        {
          "moduleId": null,
          "moduleIdentifier": null,
          "module": null,
          "moduleName": null,
          "type": "single entry",
          "userRequest": "/Users/rawbin/Documents/Projets/these/peritext/peritext-libs/ovide/services/htmlBuildBundler/application.js",
          "loc": "main"
        }
      ],
      "usedExports": true,
      "providedExports": null,
      "optimizationBailout": [
        "ModuleConcatenation bailout: Module is not an ECMAScript module"
      ],
      "depth": 0,
      "source": "throw new Error(\"Module build failed (from ./node_modules/babel-loader/lib/index.js):\\nSyntaxError: static is a reserved word in strict mode (42:12)\\n\\n\\u001b[0m \\u001b[90m 40 | \\u001b[39m    }\\u001b[33m,\\u001b[39m \\u001b[36mnull\\u001b[39m)\\u001b[33m,\\u001b[39m mountNode\\u001b[33m,\\u001b[39m \\u001b[36mfunction\\u001b[39m(){\\n \\u001b[90m 41 | \\u001b[39m      console\\u001b[33m.\\u001b[39mlog(\\u001b[32m'done hydrating'\\u001b[39m)\\n\\u001b[31m\\u001b[1m>\\u001b[22m\\u001b[39m\\u001b[90m 42 | \\u001b[39m      \\u001b[36mconst\\u001b[39m static \\u001b[33m=\\u001b[39m document\\u001b[33m.\\u001b[39mgetElementById(\\u001b[32m'static-container'\\u001b[39m)\\n \\u001b[90m    | \\u001b[39m            \\u001b[31m\\u001b[1m^\\u001b[22m\\u001b[39m\\n \\u001b[90m 43 | \\u001b[39m      setTimeout(() \\u001b[33m=>\\u001b[39m {\\n \\u001b[90m 44 | \\u001b[39m        \\u001b[36mif\\u001b[39m (static) {\\n \\u001b[90m 45 | \\u001b[39m          static\\u001b[33m.\\u001b[39mremove()\\u001b[33m;\\u001b[39m\\u001b[0m\\n\");"
    }
  ],
  "filteredModules": 0,
  "logging": {
    "webpack.buildChunkGraph.visitModules": {
      "entries": [
      ],
      "filteredEntries": 2,
      "debug": false
    }
  },
  "children": [
  ]
}